rimworld/__init__.py
rimworld/error.py
rimworld/gameversion.py
rimworld/mod.py
rimworld/patch/__init__.py
rimworld/patch/operations/add.py
rimworld/patch/operations/addmodextension.py
rimworld/patch/operations/attributeadd.py
rimworld/patch/operations/attributeremove.py
rimworld/patch/operations/attributeset.py
rimworld/patch/operations/conditional.py
rimworld/patch/operations/findmod.py
rimworld/patch/operations/insert.py
rimworld/patch/operations/op_test.py
rimworld/patch/operations/remove.py
rimworld/patch/operations/replace.py
rimworld/patch/operations/sequence.py
rimworld/patch/operations/setname.py
rimworld/patch/proto.py
rimworld/patch/result.py
rimworld/patch/serializers.py
rimworld/patch/xmlextensions/__init__.py
rimworld/patch/xmlextensions/addorreplace.py
rimworld/patch/xmlextensions/base.py
rimworld/patch/xmlextensions/safeadd.py
rimworld/util.py
rimworld/xml.py
rimworld-0.3.3.dist-info/LICENSE
rimworld-0.3.3.dist-info/METADATA
rimworld-0.3.3.dist-info/WHEEL
rimworld-0.3.3.dist-info/RECORD
