Metadata-Version: 2.1
Name: rimworld
Version: 0.3.3
Summary: 
Author: Natalia Borovskikh
Author-email: lai.tash@gmail.com
Requires-Python: >=3.12,<4.0
Classifier: Programming Language :: Python :: 3
Classifier: Programming Language :: Python :: 3.12
Requires-Dist: lxml (>=5.2.2,<6.0.0)
Requires-Dist: lxml-stubs (>=0.5.1,<0.6.0)
